impresso_text_preparation-3.0.0.dist-info/licenses/LICENSE
text_preparation/__init__.py
text_preparation/tokenization.py
text_preparation/utils.py
text_preparation/importer_scripts/__init__.py
text_preparation/importer_scripts/bculimporter.py
text_preparation/importer_scripts/blomnimporter.py
text_preparation/importer_scripts/bnfen_importer.py
text_preparation/importer_scripts/bnfimporter.py
text_preparation/importer_scripts/fedgazimporter.py
text_preparation/importer_scripts/inaimporter.py
text_preparation/importer_scripts/luximporter.py
text_preparation/importer_scripts/oliveimporter.py
text_preparation/importer_scripts/reroimporter.py
text_preparation/importer_scripts/swaimporter.py
text_preparation/importer_scripts/swissinfoimporter.py
text_preparation/importer_scripts/tetmlimporter.py
text_preparation/importers/__init__.py
text_preparation/importers/classes.py
text_preparation/importers/core.py
text_preparation/importers/detect.py
text_preparation/importers/generic_importer.py
text_preparation/importers/bcul/__init__.py
text_preparation/importers/bcul/classes.py
text_preparation/importers/bcul/detect.py
text_preparation/importers/bcul/helpers.py
text_preparation/importers/bl/__init__.py
text_preparation/importers/bl/detect.py
text_preparation/importers/bl/omni/__init__.py
text_preparation/importers/bl/omni/classes.py
text_preparation/importers/bnf/__init__.py
text_preparation/importers/bnf/classes.py
text_preparation/importers/bnf/detect.py
text_preparation/importers/bnf/helpers.py
text_preparation/importers/bnf/parsers.py
text_preparation/importers/bnf_en/__init__.py
text_preparation/importers/bnf_en/classes.py
text_preparation/importers/bnf_en/detect.py
text_preparation/importers/fedgaz/__init__.py
text_preparation/importers/fedgaz/classes.py
text_preparation/importers/fedgaz/show_canonical_boxes.py
text_preparation/importers/ina/__init__.py
text_preparation/importers/ina/classes.py
text_preparation/importers/ina/detect.py
text_preparation/importers/ina/helpers.py
text_preparation/importers/lux/__init__.py
impresso_text_preparation-3.0.0.dist-info/METADATA
impresso_text_preparation-3.0.0.dist-info/WHEEL
impresso_text_preparation-3.0.0.dist-info/entry_points.txt
impresso_text_preparation-3.0.0.dist-info/top_level.txt
impresso_text_preparation-3.0.0.dist-info/RECORD
